{"apps":[{"beta":false,"bundleIdentifier":"kalphal.us.ytmmini","developerName":"Kalphalus","downloadURL":"https://github.com/Kalphalus/YouRTubeMusiciOS/Releases/latest/YTMMini.ipa","iconURL":"https://github.com/Kalphalus/YouRTubeMusiciOS/raw/main/Sideloading/Repo/logo.ytmmini.original.png","localizedDescription":"Low Storage YouTube Music Client for those who prefer a App","name":"YTMMini","screenshotURLs":["https://github.com/Kalphalus/YouRTubeMusiciOS/raw/main/Sideloading/Repo/logo.ytmmini.original.png"],"size":1,"subtitle":"Low Storage YouTube Music Client","tintColor":"ff0000","category":"entertainment","version":"0.1m","versionDate":"2024-12-21T14:00:00-05:00","versionDescription":"Created the Repo\n\nFile doesn’t Exist"},{"beta": false,"bundleIdentifier":"kalphal.us.supportyourtube","developerName":"Kalphalus","downloadURL":"https://github.com/Kalphalus/YouRTubeMusic/Releases/latest/na.ipa","iconURL":"https://github.com/Kalphalus/YouRTubeMusiciOS/raw/main/Sideloading/Repo/logo.ytmmini.original.png","localizedDescription":"If you like YTMMini, consider donating!","name": "Support YTMMini","screenshotURLs":["https://github.com/Kalphalus/YouRTubeMusiciOS/raw/main/Sideloading/Repo/logo.ytmmini.original.png"],"size": 0,"subtitle":"If you like YTMMini, consider donating!","tintColor":"ff0000","version":"0","versionDate":"1111-11-11T11:11:11-11:11","versionDescription": "There is no donation exclusively version, if you enjoy the app, consider donating though"}],"identifier":"kalphal.us.ytmmini","name":"YTMMini","news":[],"userInfo":{}}
